django_abstractions/__init__.py
django_abstractions/admin_abstractions.py
django_abstractions/common_abstractions.py
django_abstractions/manager_abstractions.py
django_abstractions/model_abstractions.py
django_abstractions-0.0.14.dist-info/LICENSE
django_abstractions-0.0.14.dist-info/METADATA
django_abstractions-0.0.14.dist-info/WHEEL
django_abstractions-0.0.14.dist-info/top_level.txt
django_abstractions-0.0.14.dist-info/RECORD
