Metadata-Version: 2.1
Name: django-abstractions
Version: 0.0.14
Summary: Django abstractions. Bicycles out of the box.
Home-page: https://github.com/riros/django_abstractions
Author: Ivan Valenkov (Riros)
Author-email: ivanvalenkov@gmail.com
License: UNKNOWN
Platform: UNKNOWN
License-File: LICENSE
Requires-Dist: django
Requires-Dist: django-crum
Requires-Dist: django-uuslug
